{
    "attrs": {
        "icon": {
            "varType": 1,
            "value": "asset/image/picture/icon/item/Medicine_2.png",
            "copy": false
        },
        "intro": {
            "varType": 1,
            "value": "使用后恢复200点魔法值！(战斗中不消耗行动力)",
            "copy": false
        },
        "sell": {
            "varType": 0,
            "value": 25,
            "copy": false
        },
        "isUse": {
            "varType": 2,
            "value": true,
            "copy": false
        },
        "isConsumables": {
            "varType": 2,
            "value": true,
            "copy": false
        },
        "se": {
            "varType": 1,
            "value": "asset/audio/se/item/Drink_1.mp3,1,1",
            "copy": false,
            "volume": "1",
            "pitch": "1"
        },
        "callEvent": {
            "varType": 1,
            "value": "\u000558502324424_0.23898348318125628\u0005[]",
            "copy": false
        },
        "描述": {
            "varType": 1,
            "value": "",
            "copy": false
        },
        "未命名变量": {
            "varType": 1,
            "value": "",
            "copy": false
        },
        "releaseAnimation": {
            "varType": 0,
            "value": 0,
            "copy": false
        },
        "recoveryHP": {
            "varType": 0,
            "value": 0,
            "copy": false
        },
        "recoverySP": {
            "varType": 0,
            "value": 200,
            "copy": false
        },
        "addStatus": {
            "varType": 6,
            "value": [],
            "copy": false
        },
        "removeStatus": {
            "varType": 6,
            "value": [],
            "copy": false
        },
        "costActionPower": {
            "varType": 2,
            "value": false,
            "copy": false
        },
        "useType": {
            "varType": 0,
            "value": 2,
            "copy": false
        },
        "isSingleTarget": {
            "varType": 2,
            "value": true,
            "copy": false
        },
        "sellEnabled": {
            "varType": 2,
            "value": true,
            "copy": false
        }
    },
    "id": 2
}